kesacco/__init__.py
kesacco/clustpipe.py
kesacco/clustpipe_ana.py
kesacco/clustpipe_ana_plot.py
kesacco/clustpipe_common.py
kesacco/clustpipe_sim.py
kesacco/clustpipe_title.py
kesacco/Tools/__init__.py
kesacco/Tools/background.py
kesacco/Tools/build_ctools_model.py
kesacco/Tools/compact_source.py
kesacco/Tools/cubemaking.py
kesacco/Tools/make_cluster_template.py
kesacco/Tools/mcmc_common.py
kesacco/Tools/mcmc_profile.py
kesacco/Tools/mcmc_spectralimaging1.py
kesacco/Tools/mcmc_spectralimaging2.py
kesacco/Tools/mcmc_spectrum.py
kesacco/Tools/obs_setup.py
kesacco/Tools/plotting.py
kesacco/Tools/plotting_irf.py
kesacco/Tools/plotting_obsfile.py
kesacco/Tools/tools_imaging.py
kesacco/Tools/tools_onoff.py
kesacco/Tools/tools_spectral.py
kesacco/Tools/tools_timing.py
kesacco/Tools/utilities.py
kesacco-1.1.4.dist-info/LICENSE
kesacco-1.1.4.dist-info/METADATA
kesacco-1.1.4.dist-info/WHEEL
kesacco-1.1.4.dist-info/top_level.txt
kesacco-1.1.4.dist-info/RECORD
