Metadata-Version: 2.1
Name: kesacco
Version: 1.1.4
Summary: Keen Event Simulation and Analysis for CTA Cluster Observations: python code to simulate and analyse galaxy cluster data with CTA
Home-page: https://github.com/remi-adam/kesacco
Author: Remi Adam
Author-email: remi.adam@oca.eu
License: BSD
Platform: UNKNOWN
Classifier: Development Status :: 4 - Beta
Classifier: Intended Audience :: Science/Research
Classifier: Topic :: Scientific/Engineering :: Astronomy
Classifier: License :: OSI Approved :: BSD License
Classifier: Programming Language :: Python :: 3
License-File: LICENSE
Requires-Dist: numpy (>=1.6)
Requires-Dist: scipy
Requires-Dist: astropy (>=1.2.1)
Requires-Dist: matplotlib
Requires-Dist: ebltable
Requires-Dist: emcee
Requires-Dist: corner
Requires-Dist: ctools
Requires-Dist: minot
